MANIFEST.in
README.rst
requirements-tests.txt
requirements.txt
setup.cfg
setup.py
django_pivot/.forms.py.swp
django_pivot/.utils.py.swp
django_pivot/__init__.py
django_pivot/admin.py
django_pivot/apps.py
django_pivot/constants.py
django_pivot/defaults.py
django_pivot/forms.py
django_pivot/models.py
django_pivot/settings.py
django_pivot/utils.py
django_pivot/views.py
django_pivot/contrib/__init__.py
django_pivot/contrib/graphene_django_extras.py
django_pivot/contrib/rest_framework.py
django_pivot/migrations/__init__.py
django_pivot/tests/.test_forms.py.swp
django_pivot/tests/__init__.py
django_pivot/tests/factories.py
django_pivot/tests/test_forms.py
django_pivot/tests/test_rest_framework.py
django_pivot/tests/test_schema.py
django_pivot/tests/test_views.py
django_pivot/tests/test_project/__init__.py
django_pivot/tests/test_project/manage.py
django_pivot/tests/test_project/schema.py
django_pivot/tests/test_project/settings.py
django_pivot/tests/test_project/urls.py
django_pivot/tests/test_project/wsgi.py
django_pivot/tests/test_project/testapp/__init__.py
django_pivot/tests/test_project/testapp/admin.py
django_pivot/tests/test_project/testapp/apps.py
django_pivot/tests/test_project/testapp/filtersets.py
django_pivot/tests/test_project/testapp/models.py
django_pivot/tests/test_project/testapp/tests.py
django_pivot/tests/test_project/testapp/views.py
django_pivot/tests/test_project/testapp/viewsets.py
django_pivot/tests/test_project/testapp/migrations/0001_initial.py
django_pivot/tests/test_project/testapp/migrations/__init__.py
django_pivot/tests/test_project/testapp/templates/pivot.html
django_pivot2.egg-info/PKG-INFO
django_pivot2.egg-info/SOURCES.txt
django_pivot2.egg-info/dependency_links.txt
django_pivot2.egg-info/requires.txt
django_pivot2.egg-info/top_level.txt