Metadata-Version: 2.1
Name: django-pivot2
Version: 0.2.10
Summary: Easily browse your Django models
Home-page: https://github.com/cloudmercato/django-pivot
Author: Anthony Monthe (2uluPro)
Author-email: anthony@cloud-mercato.com
License: BSD
Keywords: django,web,data,html
Platform: UNKNOWN
Classifier: Development Status :: 4 - Beta
Classifier: Environment :: Web Environment
Classifier: Environment :: Console
Classifier: Framework :: Django
Classifier: Intended Audience :: Developers
Classifier: License :: OSI Approved :: BSD License
Classifier: Natural Language :: English
Classifier: Operating System :: OS Independent
Classifier: Programming Language :: Python :: 3
Classifier: Programming Language :: Python :: 3.4
Classifier: Programming Language :: Python :: 3.5
